byteblower/test_cases/low_latency/.gitignore
byteblower/test_cases/low_latency/__init__.py
byteblower/test_cases/low_latency/__main__.py
byteblower/test_cases/low_latency/_arguments.py
byteblower/test_cases/low_latency/_config_file.py
byteblower/test_cases/low_latency/_definitions.py
byteblower/test_cases/low_latency/_endpoint_factory.py
byteblower/test_cases/low_latency/_flow_factory.py
byteblower/test_cases/low_latency/_lld.py
byteblower/test_cases/low_latency/_port_factory.py
byteblower/test_cases/low_latency/_scouting_flow.py
byteblower/test_cases/low_latency/_stream_data_gatherer.py
byteblower/test_cases/low_latency/_version.py
byteblower/test_cases/low_latency/cli.py
byteblower/test_cases/low_latency/csvaggregator.py
byteblower/test_cases/low_latency/dynamic_frameblastingflow.py
byteblower/test_cases/low_latency/exceptions.py
byteblower/test_cases/low_latency/l4s_analysers.py
byteblower/test_cases/low_latency/l4s_frameblastingflow.py
byteblower/test_cases/low_latency/outlier_latency_cdf_analyser.py
byteblower_test_cases_low_latency-1.2.2.dist-info/entry_points.txt
byteblower_test_cases_low_latency-1.2.2.dist-info/LICENSE
byteblower_test_cases_low_latency-1.2.2.dist-info/WHEEL
byteblower_test_cases_low_latency-1.2.2.dist-info/METADATA
byteblower_test_cases_low_latency-1.2.2.dist-info/RECORD
